fa.v
module fa(
    input a,b,c,
    output sum,cout
);
assign sum = a ^ b ^ c;
assign cout = (a & b) | (c & (a ^ b) );
endmodule

pm_para_as.v
`timescale 1ns/1ps
module p_as #(parameter width = 16)(
    input [width-1:0]a,b,           
    input cin,                      // mode = 0 for addition mode = 1 for subtraction
    output [width-1:0] sum,         // output is width - 1 as carry has separate flag
    output cout                     // carry generated
);

wire [width:0]carry;                //carry is width + 1 bits wide as it includes cin
assign carry[0] = cin;

wire [width-1:0]b_inverse;
assign b_inverse = b ^ {width{cin}}; //{width{cin}} produces width bits of cin, hence every bit of b is XORed with cin

genvar i;
generate
    for(i = 0; i < width; i = i + 1) begin: for_loop
        fa my_fa(
            .a (a[i]),
            .b (b_inverse[i]),
            .c (carry[i]),
            .sum (sum[i]),
            .cout(carry[i+1])
        );
    end
endgenerate
assign cout = carry[width];
endmodule

pm_para_as_tb.v
`timescale 1ns/1ps
module p_as_tb();
localparam width = 16;
reg [width-1:0]a_tb, b_tb;
reg cin_tb;
wire [width-1:0]sum_tb;
wire cout_tb;

p_as #(.width(width)) dut(
    .a(a_tb),
    .b(b_tb),
    .cin(cin_tb),
    .sum(sum_tb),
    .cout(cout_tb)
);

integer i;
initial begin
    $dumpfile("sim.vcd");
    $dumpvars(0,p_as_tb);
    cin_tb = 0;
    for(i = 0; i < 5; i = i + 1) begin
        a_tb = $urandom_range(100,1000);
        b_tb = $urandom_range(100,1000);
        #10;
        $display("time = %0t | %d + %d = %d | cout = %b", $time, a_tb, b_tb, sum_tb, cout_tb);
    end

    cin_tb = 1;
    for(i = 0; i < 5; i = i + 1) begin
        a_tb = $urandom_range(100,1000);
        b_tb = $urandom_range(100,1000);
        #10;
        $display("time = %0t | %d - %d = %d | cout = %b", $time, a_tb, b_tb, sum_tb, cout_tb);
    end
    $finish;
end

endmodule

sim.vcd
$date
	Sat Mar 21 21:18:06 2026
$end
$version
	Icarus Verilog
$end
$timescale
	1ps
$end
$scope module p_as_tb $end
$var wire 16 ! sum_tb [15:0] $end
$var wire 1 " cout_tb $end
$var parameter 32 # width $end
$var reg 16 $ a_tb [15:0] $end
$var reg 16 % b_tb [15:0] $end
$var reg 1 & cin_tb $end
$var integer 32 ' i [31:0] $end
$scope module dut $end
$var wire 16 ( a [15:0] $end
$var wire 16 ) b [15:0] $end
$var wire 16 * b_inverse [15:0] $end
$var wire 1 & cin $end
$var wire 16 + sum [15:0] $end
$var wire 1 " cout $end
$var wire 17 , carry [16:0] $end
$var parameter 32 - width $end
$scope begin for_loop[0] $end
$var parameter 2 . i $end
$scope module my_fa $end
$var wire 1 / a $end
$var wire 1 0 b $end
$var wire 1 1 c $end
$var wire 1 2 cout $end
$var wire 1 3 sum $end
$upscope $end
$upscope $end
$scope begin for_loop[1] $end
$var parameter 2 4 i $end
$scope module my_fa $end
$var wire 1 5 a $end
$var wire 1 6 b $end
$var wire 1 7 c $end
$var wire 1 8 cout $end
$var wire 1 9 sum $end
$upscope $end
$upscope $end
$scope begin for_loop[2] $end
$var parameter 3 : i $end
$scope module my_fa $end
$var wire 1 ; a $end
$var wire 1 < b $end
$var wire 1 = c $end
$var wire 1 > cout $end
$var wire 1 ? sum $end
$upscope $end
$upscope $end
$scope begin for_loop[3] $end
$var parameter 3 @ i $end
$scope module my_fa $end
$var wire 1 A a $end
$var wire 1 B b $end
$var wire 1 C c $end
$var wire 1 D cout $end
$var wire 1 E sum $end
$upscope $end
$upscope $end
$scope begin for_loop[4] $end
$var parameter 4 F i $end
$scope module my_fa $end
$var wire 1 G a $end
$var wire 1 H b $end
$var wire 1 I c $end
$var wire 1 J cout $end
$var wire 1 K sum $end
$upscope $end
$upscope $end
$scope begin for_loop[5] $end
$var parameter 4 L i $end
$scope module my_fa $end
$var wire 1 M a $end
$var wire 1 N b $end
$var wire 1 O c $end
$var wire 1 P cout $end
$var wire 1 Q sum $end
$upscope $end
$upscope $end
$scope begin for_loop[6] $end
$var parameter 4 R i $end
$scope module my_fa $end
$var wire 1 S a $end
$var wire 1 T b $end
$var wire 1 U c $end
$var wire 1 V cout $end
$var wire 1 W sum $end
$upscope $end
$upscope $end
$scope begin for_loop[7] $end
$var parameter 4 X i $end
$scope module my_fa $end
$var wire 1 Y a $end
$var wire 1 Z b $end
$var wire 1 [ c $end
$var wire 1 \ cout $end
$var wire 1 ] sum $end
$upscope $end
$upscope $end
$scope begin for_loop[8] $end
$var parameter 5 ^ i $end
$scope module my_fa $end
$var wire 1 _ a $end
$var wire 1 ` b $end
$var wire 1 a c $end
$var wire 1 b cout $end
$var wire 1 c sum $end
$upscope $end
$upscope $end
$scope begin for_loop[9] $end
$var parameter 5 d i $end
$scope module my_fa $end
$var wire 1 e a $end
$var wire 1 f b $end
$var wire 1 g c $end
$var wire 1 h cout $end
$var wire 1 i sum $end
$upscope $end
$upscope $end
$scope begin for_loop[10] $end
$var parameter 5 j i $end
$scope module my_fa $end
$var wire 1 k a $end
$var wire 1 l b $end
$var wire 1 m c $end
$var wire 1 n cout $end
$var wire 1 o sum $end
$upscope $end
$upscope $end
$scope begin for_loop[11] $end
$var parameter 5 p i $end
$scope module my_fa $end
$var wire 1 q a $end
$var wire 1 r b $end
$var wire 1 s c $end
$var wire 1 t cout $end
$var wire 1 u sum $end
$upscope $end
$upscope $end
$scope begin for_loop[12] $end
$var parameter 5 v i $end
$scope module my_fa $end
$var wire 1 w a $end
$var wire 1 x b $end
$var wire 1 y c $end
$var wire 1 z cout $end
$var wire 1 { sum $end
$upscope $end
$upscope $end
$scope begin for_loop[13] $end
$var parameter 5 | i $end
$scope module my_fa $end
$var wire 1 } a $end
$var wire 1 ~ b $end
$var wire 1 !" c $end
$var wire 1 "" cout $end
$var wire 1 #" sum $end
$upscope $end
$upscope $end
$scope begin for_loop[14] $end
$var parameter 5 $" i $end
$scope module my_fa $end
$var wire 1 %" a $end
$var wire 1 &" b $end
$var wire 1 '" c $end
$var wire 1 (" cout $end
$var wire 1 )" sum $end
$upscope $end
$upscope $end
$scope begin for_loop[15] $end
$var parameter 5 *" i $end
$scope module my_fa $end
$var wire 1 +" a $end
$var wire 1 ," b $end
$var wire 1 -" c $end
$var wire 1 ." cout $end
$var wire 1 /" sum $end
$upscope $end
$upscope $end
$upscope $end
$upscope $end
$enddefinitions $end
$comment Show the parameter values. $end
$dumpall
b1111 *"
b1110 $"
b1101 |
b1100 v
b1011 p
b1010 j
b1001 d
b1000 ^
b111 X
b110 R
b101 L
b100 F
b11 @
b10 :
b1 4
b0 .
b10000 -
b10000 #
$end
#0
$dumpvars
0/"
0."
0-"
0,"
0+"
0)"
0("
0'"
0&"
0%"
0#"
0""
0!"
0~
0}
0{
0z
0y
0x
0w
0u
0t
0s
0r
0q
0o
0n
0m
0l
0k
1i
0h
0g
0f
1e
1c
0b
0a
1`
0_
1]
0\
1[
0Z
0Y
0W
1V
0U
1T
1S
1Q
0P
0O
0N
1M
0K
0J
0I
0H
0G
1E
0D
1C
0B
0A
1?
1>
1=
1<
1;
09
18
07
16
15
13
02
01
10
0/
b10001100 ,
b1110101101 +
b101000111 *
b101000111 )
b1001100110 (
b0 '
0&
b101000111 %
b1001100110 $
0"
b1110101101 !
$end
#10000
1U
0E
1P
0C
0Q
1]
0>
1O
1[
19
1J
0W
1V
17
03
b11100110 ,
12
1?
0K
b110000110 !
b110000110 +
0i
0<
1H
0T
b100010011 *
1/
0;
1G
0e
b100010011 %
b100010011 )
b1110011 $
b1110011 (
b1 '
#20000
1K
1o
0]
1I
1m
09
1C
0[
1D
1h
07
1>
0V
13
b10001111100 ,
02
1?
1E
1W
b10101011101 !
b10101011101 +
0i
1<
1B
1f
b1100011111 *
0/
1;
1A
0S
1e
b1100011111 %
b1100011111 )
b1000111110 $
b1000111110 (
b10 '
#30000
0O
0J
0?
0I
0W
0=
0D
0U
0o
03
19
08
1K
1]
0P
0g
0m
1E
0Q
1c
0b
b110011010 !
b110011010 +
0i
b1000 ,
0h
00
06
0B
0H
1Z
0`
0f
b10000100 *
0A
0M
1_
0e
b10000100 %
b10000100 )
b100010110 $
b100010110 (
b11 '
#40000
1O
1J
1W
1o
1U
1m
1I
1P
0]
1h
0C
1D
13
19
1?
b10001110000 ,
0>
0E
0K
1Q
0c
b10001100111 !
b10001100111 +
0i
16
1B
1H
1N
0Z
1f
b1000111110 *
1/
05
0;
1A
0G
1M
0_
1e
b1000111110 %
b1000111110 )
b1000101001 $
b1000101001 (
b100 '
#50000
1"
1."
1-"
1("
1'"
1""
1!"
1z
1g
1b
1y
1Q
1t
1O
1a
1=
1J
1\
18
1s
0K
09
1m
1n
1C
1I
1[
17
0c
0i
1h
0o
0u
0{
0#"
0)"
0/"
1?
1>
0E
1D
1V
0]
12
b1100100 !
b1100100 +
03
10
06
0H
1T
1`
0f
1l
1r
1x
1~
1&"
1,"
0/
15
1;
0A
1G
1S
1Y
11
b1111110101101101 *
b1010010010 %
b1010010010 )
b1011110110 $
b1011110110 (
b11111111111111111 ,
1&
b0 '
#60000
0I
0W
0D
0U
0P
07
0C
02
0>
0=
0O
13
1]
08
b11111111110000001 ,
0J
19
0?
1E
0K
1Q
b10101011 !
b10101011 +
0c
00
16
0<
0B
1Z
0`
b1111110011100010 *
05
0;
1A
0G
0M
1_
b1100011101 %
b1100011101 )
b1111001000 $
b1111001000 (
b1 '
#70000
1g
1b
0c
1U
1a
1P
1\
0Q
1C
1I
1O
1[
1>
1E
1D
1J
0W
1V
0]
1i
1=
09
b11111111111111101 ,
18
1?
b1000011101 !
b1000011101 +
1K
1<
1B
1H
0T
0Z
1f
b1111111000111110 *
15
1;
1G
b111000001 %
b111000001 )
b1111011110 $
b1111011110 (
b10 '
#80000
0U
0P
1Q
0O
0J
0C
0I
0>
0D
0W
0=
09
b11111111110000001 ,
08
0?
0E
1K
b110001 !
b110001 +
0i
06
0<
0B
1T
b1111111001110000 *
05
0;
0A
0G
0e
b110001111 %
b110001111 )
b111000000 $
b111000000 (
b11 '
#90000
1?
1=
18
1]
17
12
1I
03
1D
1O
1U
1[
09
0E
0K
1J
0Q
1P
0W
b11111111111110111 ,
1V
b1010000100 !
b1010000100 +
1i
10
1B
0H
0N
1Z
b1111111011001001 *
15
1A
1G
1M
0S
1e
b100110110 %
b100110110 )
b1110111010 $
b1110111010 (
b100 '
#100000
b101 '
